{"__typename": "Application", "id": "1312603832098804", "__isAppStoreItem": "Application", "cover_landscape_image": {"uri": "https://scontent-iad3-1.oculuscdn.com/v/t64.5771-25/11162745_1719771891578785_1379979740_n.jpg?stp=dst-jpg_q92_s720x720_tt6&_nc_cat=101&ccb=1-7&_nc_sid=6e7a0a&_nc_ohc=5LdhaBZ6DIsQ7kNvwGAnp4l&_nc_oc=AdmWorgy1bh70KxJq-Z1CLo1881MaxmQqqqFlly9IVqKdflVHGfVpEXXgf6EKMgK_fg&_nc_zt=3&_nc_ht=scontent-iad3-1.oculuscdn.com&oh=00_AfV_mlr9OrnsBSUMIsr079xvqWV98rg0nlmGHs9iB1zB1w&oe=68AAE6A4", "height": 405, "width": 720}, "cover_square_image": {"uri": "https://scontent-iad3-2.oculuscdn.com/v/t64.5771-25/12449016_500595363474300_32568515_n.jpg?stp=dst-jpg_q92_s720x720_tt6&_nc_cat=103&ccb=1-7&_nc_sid=6e7a0a&_nc_ohc=fKhyRyR7DkwQ7kNvwE3E4xM&_nc_oc=AdkwM9aCKHyJjlhEhek3JqXcPqSDetuTMwRbAUiUK1-JZQz7yWRyyHwm6yjSWbaeEg8&_nc_zt=3&_nc_ht=scontent-iad3-2.oculuscdn.com&oh=00_AfUx13lKUQ591Kh-_28MMdUjoKAhSkh5KBO9qIt8vguZNg&oe=68AB0BC8", "height": 720, "width": 720}, "cover_portrait_image": {"uri": "https://scontent-iad3-2.oculuscdn.com/v/t64.5771-25/12138771_210710569294625_857228750_n.jpg?stp=dst-jpg_q92_s515x515_tt6&_nc_cat=100&ccb=1-7&_nc_sid=6e7a0a&_nc_ohc=RCYXBklpEbYQ7kNvwEEROHa&_nc_oc=AdkQFJ5CSrJdwH1CsxBfIkIVMS9-92GcHlTGCnZ84tfCSXdPnDYbiIjU93kfztcfV5Y&_nc_zt=3&_nc_ht=scontent-iad3-2.oculuscdn.com&oh=00_AfWvsaRtW-h3uPPq3viGvbDtrR4f4H3V9d2ensHQJ8iAHw&oe=68AB0736", "height": 515, "width": 360}, "display_name": "Escape From Bunker 14", "accolade_badges": [], "display_item_type": "Application", "category_name": "", "genre_names": [], "quality_rating_aggregate": 2.6595744680851, "quest_plus_metadata_tags": [], "is_viewer_entitled": false, "current_offer": {"__typename": "AppStoreOffer", "offer_type": "APPSTORE_OFFER", "id": "1002777776482332", "price": {"currency": "USD", "offset_amount": "299", "formatted": "$2.99"}, "strikethrough_price": null, "promo_benefit": null, "end_time": 0, "show_timer": false}, "viewer_entitlement": null, "current_trial_offer": null, "viewer_has_preorder": false, "canonical_name": "tiriam-immersive-media-escape-from-bunker-14", "release_info": {"display_date": "March 30, 2016"}, "icon_image": {"uri": "https://scontent-iad3-2.oculuscdn.com/v/t64.5771-25/12138836_182901612094524_398616853_n.jpg?stp=dst-jpg_q92_s160x160_tt6&_nc_cat=100&ccb=1-7&_nc_sid=6e7a0a&_nc_ohc=rbxNPJxQSzgQ7kNvwHjpikB&_nc_oc=Admd1PgxzpuqqEIKT6J-Fn2z5Q8sBKOKO6bvyQpVesKtPapLFJo5alnr8YEeDkTPpPI&_nc_zt=3&_nc_ht=scontent-iad3-2.oculuscdn.com&oh=00_AfUhzFU1WCqF-ON-s5mtSNPF5cl4ltls7-Tc5Rn4YdUihw&oe=68AAE57B", "height": 160, "width": 160}}