{"data": {"node": {"__typename": "Application", "id": "8285675901524470", "organization": {"id": "1557924888266299", "viewer_permissions": [], "application_groupings": {"nodes": [{"viewer_has_update_access": false, "full_applications": {"nodes": [{"id": "8285675901524470"}]}, "id": "433272632578158"}]}}, "firstRevision": {"nodes": [{"application": {"id": "8285675901524470", "release_date": 1729864800, "is_concept": false, "platform": "ANDROID_6DOF", "scheduled_offers": {"count": 5}, "liveChannel": {"nodes": [{"latest_supported_binary": {"__typename": "AndroidBinary", "binary_test_results": {"nodes": []}, "id": "24864145893250876"}, "id": "823519099854924"}]}}, "binary": {"__typename": "AndroidBinary", "__isAppBinary": "AndroidBinary", "binary_application": {"__typename": "Application", "id": "8285675901524470", "is_concept": false, "latest_released_binary": {"__typename": "AndroidBinary", "id": "24864145893250876"}, "release_status": "RELEASED"}, "id": "24864145893250876", "version": "1.0.0", "version_code": 1000, "release_status": "RELEASED", "status": "APPROVED"}, "live_binary": null, "created_date": 1760132364, "id": "24736985229300277", "is_initial_release": false, "name_with_fallback": "v5", "pdp_metadata_with_fallback": {"version": 2, "application": {"is_concept": false, "latest_released_pdp_metadata": {"id": "24872576655741133"}, "release_status": "RELEASED", "id": "8285675901524470"}, "id": "24872576655741133", "release_status": "RELEASED", "status": "APPROVED"}, "release_date": null, "administration_status": "APPROVED", "is_first": false, "release_status": "RELEASED", "release_type": "SCHEDULED", "pdp_metadata": {"application": {"default_locale": "en_US", "id": "8285675901524470", "is_first_party": false, "enables_in_app_ads": false, "is_concept": false, "platform": "ANDROID_6DOF"}, "iarc_cert": {"id": "1167826477849822"}, "iarc_email": null, "msrp": null, "translations": {"nodes": [{"images": {"nodes": [{"file_name": "TikTokInsta016.png", "id": "2797208537150026", "image_type": "APP_IMG_HERO", "uri": "https://scontent-sjc3-1.oculuscdn.com/v/t64.5771-25/491827567_2797208543816692_6638848380506301003_n.png?_nc_cat=105&ccb=1-7&_nc_sid=6e7a0a&_nc_ohc=YEIRJSdX7sAQ7kNvwH72Sz6&_nc_oc=AdnVPhS3bivn9E0NIjRcPZfLWsA6_4VqNWjGdhZlucBJZae1ffmQYrPFNLF4DEC3B7o&_nc_zt=3&_nc_ht=scontent-sjc3-1.oculuscdn.com&oh=00_Afr_feW41OXLVtDrbYIPY__RWVg1wCeTbjgadQzexlTwEA&oe=695BABFD"}, {"file_name": "Logo_1440x1440.png", "id": "1893896191018730", "image_type": "APP_IMG_COVER_SQUARE", "uri": "https://scontent-sjc6-1.oculuscdn.com/v/t64.5771-25/86604447_1893896194352063_1398425080220018222_n.png?_nc_cat=111&ccb=1-7&_nc_sid=6e7a0a&_nc_ohc=MxXB2tOy0FkQ7kNvwF_FLjJ&_nc_oc=AdlcUBZaRGeRpmK5AvOaKYoIKaMhplKOLF4OpeET8C9V28ZrEcgvWy7AnyMGwhvCvCI&_nc_zt=3&_nc_ht=scontent-sjc6-1.oculuscdn.com&oh=00_AfqxAUTzFrx-AAPFNOW9ByHcGphUkDtyANU4zhbaWDevFA&oe=695BB42E"}, {"file_name": "TikTokInsta014.png", "id": "1515361486163411", "image_type": "APP_IMG_COVER_LANDSCAPE", "uri": "https://scontent-sjc6-1.oculuscdn.com/v/t64.5771-25/491823910_1515361489496744_2134293509700418087_n.png?_nc_cat=104&ccb=1-7&_nc_sid=6e7a0a&_nc_ohc=zGGSndr_W1AQ7kNvwEdneZn&_nc_oc=AdmCaIcyOuq8hKWQmwKULJYhHmLNdMrWSP6Dov8U3da4NRzLzQdEEsA5l3qznWCTjJI&_nc_zt=3&_nc_ht=scontent-sjc6-1.oculuscdn.com&oh=00_AfoQjMR0KDKWZ42Nwf9H1_mZQTSKS_VvTMSoBaKqb7J_Cw&oe=695BBF15"}, {"file_name": "Logo_1008x1440.png", "id": "1263381491292105", "image_type": "APP_IMG_COVER_PORTRAIT", "uri": "https://scontent-sjc3-1.oculuscdn.com/v/t64.5771-25/39035391_1263381494625438_797498569855565140_n.png?_nc_cat=110&ccb=1-7&_nc_sid=6e7a0a&_nc_ohc=E-YHFHrR_LoQ7kNvwERof9U&_nc_oc=Adk9u2D5DlzU7kvUsvrbiVsUbCsPKcek6a1q-YYRFQouvb1Xk2bQKjetNRSbgSf5YR0&_nc_zt=3&_nc_ht=scontent-sjc3-1.oculuscdn.com&oh=00_AfongWok9-Sh6bO-G0brr555L-zURdEfaYQIWv9IxJrhRA&oe=695BB951"}, {"file_name": "Logo.png", "id": "1151631356383364", "image_type": "APP_IMG_LOGO_TRANSPARENT", "uri": "https://scontent-sjc6-1.oculuscdn.com/v/t64.5771-25/75250457_1151631359716697_1929581514997661644_n.png?_nc_cat=107&ccb=1-7&_nc_sid=6e7a0a&_nc_ohc=5gSqZzL56PIQ7kNvwGtCj-s&_nc_oc=Adk6mI_jzJvTAzY0q34aR5F996xEcFDkiZVEXhqX9ms4zS2ww30yoVa1uZPnL6q5rkA&_nc_zt=3&_nc_ht=scontent-sjc6-1.oculuscdn.com&oh=00_Afrurb74FDj-bhdxJFFLn3rVvbNKWFwSmGnqB4WWOh-ctg&oe=695BA6FD"}, {"file_name": "Logo_512x512.png", "id": "405262315657101", "image_type": "APP_IMG_ICON", "uri": "https://scontent-sjc6-1.oculuscdn.com/v/t64.5771-25/38974854_405262318990434_8156810984127282611_n.png?_nc_cat=111&ccb=1-7&_nc_sid=6e7a0a&_nc_ohc=mP_TxoGC5zgQ7kNvwH0USjk&_nc_oc=Adl-RGLPNDcqi1Yw4FvgkIpptrZrmd7CJzIwERrHuE49gyCWcDlr4QSgQzxw-0GRfQE&_nc_zt=3&_nc_ht=scontent-sjc6-1.oculuscdn.com&oh=00_AfqjgcRPU44_33_AM5m33MU6dZPr0HDyo-uZO86mOjIzog&oe=695BB8BA"}]}, "id": "828611959690104", "locale": "en_US", "screenshots": [{"file_name": "Prev3.png", "id": "878645664451022", "uri": "https://scontent-sjc6-1.oculuscdn.com/v/t64.5771-25/39031325_878645667784355_2494646882430881744_n.png?_nc_cat=101&ccb=1-7&_nc_sid=6e7a0a&_nc_ohc=kCP1lCPJs84Q7kNvwFb2FFG&_nc_oc=AdloeFK_ltqJRCCg-_M5_yg4TpYe0LBvonxc1Ll__HeHpDbR_zNjW38LLLjmXJGW3Q0&_nc_zt=3&_nc_ht=scontent-sjc6-1.oculuscdn.com&oh=00_AfqS2jQnDAd212AA1UaRbz1_Kfn-JvyRgqxbFsKA7Yh4rg&oe=695BA766"}, {"file_name": "Prev4.png", "id": "507225855588758", "uri": "https://scontent-sjc6-1.oculuscdn.com/v/t64.5771-25/38982458_507225858922091_3504272917839192764_n.png?_nc_cat=111&ccb=1-7&_nc_sid=6e7a0a&_nc_ohc=7BRAmcZj4a8Q7kNvwGMCnZE&_nc_oc=Admg5wSHZ6tnqlQ2V05AmQ9RgsmpiT0H_Ir_-FJe27_oU8R1XfhxA-R9N3_y4i_qodU&_nc_zt=3&_nc_ht=scontent-sjc6-1.oculuscdn.com&oh=00_AfrVgINim4ZWGnPacVHw6Etp8cFa8Lc8cRqpbOFyrMDYaQ&oe=695B9CF6"}, {"file_name": "TikTokInsta018.png", "id": "1187275206640951", "uri": "https://scontent-sjc6-1.oculuscdn.com/v/t64.5771-25/491823930_1187275209974284_7438486235599157867_n.png?_nc_cat=108&ccb=1-7&_nc_sid=6e7a0a&_nc_ohc=3AlOYKlkCFsQ7kNvwGQRVov&_nc_oc=AdnIw7LG_LYbAuIlYWKZ2m92CaQlsj8gVkpk1Wvw7SV1Irnqz1WbfyyQ3VlfBsE9sg8&_nc_zt=3&_nc_ht=scontent-sjc6-1.oculuscdn.com&oh=00_AfqWcPOm5DZ8gA1u2IQ5ck3ilKTMV6CAVWKyubdlF6Oo7A&oe=695BBB9A"}, {"file_name": "Home002.png", "id": "2161226227737252", "uri": "https://scontent-sjc3-1.oculuscdn.com/v/t64.5771-25/491819982_2161226231070585_2515218030888064740_n.png?_nc_cat=106&ccb=1-7&_nc_sid=6e7a0a&_nc_ohc=_-RaI14A6JsQ7kNvwFeS7QY&_nc_oc=AdntjBTMF40QmwIbftGdPykrDXA2Iw_ZmTN1KHChT_SUam3lW1_4v0WUQkrJkgtWciI&_nc_zt=3&_nc_ht=scontent-sjc3-1.oculuscdn.com&oh=00_AfrEnjSTiWrwZOJUG5kUzaGnNzNhwul69V0na80ltL5PNQ&oe=695BC146"}, {"file_name": "Prev1.png", "id": "426904343309550", "uri": "https://scontent-sjc3-1.oculuscdn.com/v/t64.5771-25/39036669_426904346642883_7919296481189995880_n.png?_nc_cat=100&ccb=1-7&_nc_sid=6e7a0a&_nc_ohc=rdXXMMfhz-MQ7kNvwEeV8ts&_nc_oc=AdmRXBjI6IQgRANb5YHII_pEESlK9exnFkBb9P5fF-FRunR0EYJJYN8cNc1TIFvTmWQ&_nc_zt=3&_nc_ht=scontent-sjc3-1.oculuscdn.com&oh=00_AfpIJ2fAh_CDpsybM1hWTxnKY6yp4QJMtd1PSCsGNQQyeg&oe=695BAC25"}], "video_trailer": null, "video_trailer_thumbnail": {"file_name": "TikTokInsta014.png", "id": "1575020750535273", "uri": "https://scontent-sjc3-1.oculuscdn.com/v/t64.5771-25/491818885_1575020757201939_2334752875390600036_n.png?_nc_cat=100&ccb=1-7&_nc_sid=6e7a0a&_nc_ohc=RKV6QsQRlOgQ7kNvwErZDnd&_nc_oc=AdnG9ZKNcBsCWhWpwcV-555utsRSbFzUV4sQfAVCt5ToOsd86rQT7Wstb_CFaT5fV30&_nc_zt=3&_nc_ht=scontent-sjc3-1.oculuscdn.com&oh=00_AfpX6gIz7J05fHL5ltw6r64h5rRK8nHhE6vrtSWjTyPj6A&oe=695BBF6D"}, "display_name": "HandTastic", "keywords": ["Obstacle", "racing", "fall", "hand", "social"], "long_description": "Welcome to Handtastic!\n\nGet ready to embark on a thrilling hand-powered adventure like no other! Grab, climb, and leap your way through a colorful world filled with exciting challenges and hilarious antics.\n\nIn Handtastic, you take control of adorable creatures with capsule-formed bodies, lively arms, and insatiable curiosity. Step into their wacky world, where the competition is fierce and the fun is endless.\n\nEngage in heart-pumping multiplayer matches across a variety of whimsical maps. Race to the finish line and outlast your opponents in your quest for hand-powered glory.\n\nJoin forces with friends in our spaceship-themed lobby, where you can team up, strategize, and dive into the action together. Embrace the silliness, enjoy the colorful visuals, and groove to the upbeat soundtracks that will keep your spirits high.\n\nSo, are you ready to unleash the power of your hands?\n\nIt's time to go hand-in-hand with excitement and embark on an unforgettable adventure in Handtastic!", "short_description": "Get ready to embark on a thrilling hand-powered adventure like no other! Grab, climb, and leap your way through a colorful world filled with exciting challenges and hilarious antics.\n\nEngage in heart-pumping multiplayer matches across a variety of whimsical maps in your quest for hand-powered glory.\n\nSo, are you ready to unleash the power of your hands? It's time to go hand-in-hand with excitement and embark on an unforgettable adventure in Handtastic!"}]}, "developer_name": null, "developer_privacy_policy_url": "https://handtasticvr.com/privacy-policy", "developer_terms_of_service_url": "https://handtasticvr.com/terms-of-service", "publisher_name": "Costo Games", "support_website_url": "https://handtasticvr.com/support", "website_url": "https://handtasticvr.com/", "category": null, "comfort_rating": "COMFORTABLE_FOR_SOME", "comfort_tags": [], "context_category": {"id": "2743326035925534", "context_category": "GAMES"}, "context_topics": [{"id": "459781504968480"}, {"id": "1700921480735423"}, {"id": "1023770785722696"}, {"id": "1592192974313489"}, {"id": "528142316460358"}, {"id": "2710427532541308"}], "external_subscription_type": "NOT_REQUIRED", "genres": [], "has_in_app_ads": null, "internet_connection": "REQUIRED", "play_area": "NO_MOVEMENT", "recommended_graphics": null, "recommended_memory_gb": null, "recommended_processor": null, "supported_in_app_languages": ["en"], "supported_input_devices": ["OCULUS_TOUCH"], "supported_player_modes": ["STANDING", "ROOM_SCALE"], "supported_tracking_modes": [], "user_interaction_modes": ["MULTI_USER", "SINGLE_USER", "CO_OP"], "id": "24872576655741133"}, "review_messages": []}]}, "cover_square_image": {"uri": "https://scontent-sjc6-1.oculuscdn.com/v/t64.5771-25/86604447_1893896194352063_1398425080220018222_n.png?stp=dst-png_s360x360&_nc_cat=111&ccb=1-7&_nc_sid=6e7a0a&_nc_ohc=MxXB2tOy0FkQ7kNvwF_FLjJ&_nc_oc=AdlcUBZaRGeRpmK5AvOaKYoIKaMhplKOLF4OpeET8C9V28ZrEcgvWy7AnyMGwhvCvCI&_nc_zt=3&_nc_ht=scontent-sjc6-1.oculuscdn.com&oh=00_AfpezEM8AjvPeEFHiR4UIEVdvzo9OHXEV_LOB6sTFfO6Gg&oe=695BB42E"}, "is_concept": false, "is_test": false, "is_trial_offer_valid": false, "display_name": "HandTastic", "platform": "ANDROID_6DOF", "context_category": {"context_category": "GAMES", "id": "2743326035925534"}, "context_topics": [{"topic_name": "Action", "id": "459781504968480"}, {"topic_name": "Party Game", "id": "1700921480735423"}, {"topic_name": "Hangout", "id": "1023770785722696"}, {"topic_name": "Arcade", "id": "1592192974313489"}, {"topic_name": "Platformer", "id": "528142316460358"}, {"topic_name": "Fighting", "id": "2710427532541308"}], "release_date": 1729864800, "lastRevision": {"nodes": [{"id": "8285675951524465", "release_type": "SCHEDULED", "administration_status": "APPROVED", "pdp_metadata": {"application": {"default_locale": "en_US", "id": "8285675901524470", "is_first_party": false, "enables_in_app_ads": false, "is_concept": false, "platform": "ANDROID_6DOF"}, "iarc_cert": {"id": "1167826477849822"}, "iarc_email": null, "msrp": null, "translations": {"nodes": [{"images": {"nodes": [{"file_name": "Logo_1080x360.png", "id": "7758863464220285", "image_type": "APP_IMG_SMALL_LANDSCAPE", "uri": "https://scontent-sjc6-1.oculuscdn.com/v/t64.5771-25/39031547_7758863477553617_7645528369482826855_n.png?_nc_cat=109&ccb=1-7&_nc_sid=6e7a0a&_nc_ohc=AEuW6aQD2Q8Q7kNvwEo9TMI&_nc_oc=Adnho6Og4z9rufU2i5sS3uRbmI-nQ5BdP70mMJknB0P1t6dwK7hTYlyG9nvcqwNuy6s&_nc_zt=3&_nc_ht=scontent-sjc6-1.oculuscdn.com&oh=00_AfrWYRAtjFzLWv_2AUbkc45dMwE0aMNzhGPFKcU6hePcJA&oe=695BAFDD"}, {"file_name": "Logo_1440x1440.png", "id": "1893896191018730", "image_type": "APP_IMG_COVER_SQUARE", "uri": "https://scontent-sjc6-1.oculuscdn.com/v/t64.5771-25/86604447_1893896194352063_1398425080220018222_n.png?_nc_cat=111&ccb=1-7&_nc_sid=6e7a0a&_nc_ohc=MxXB2tOy0FkQ7kNvwF_FLjJ&_nc_oc=AdlcUBZaRGeRpmK5AvOaKYoIKaMhplKOLF4OpeET8C9V28ZrEcgvWy7AnyMGwhvCvCI&_nc_zt=3&_nc_ht=scontent-sjc6-1.oculuscdn.com&oh=00_AfqxAUTzFrx-AAPFNOW9ByHcGphUkDtyANU4zhbaWDevFA&oe=695BB42E"}, {"file_name": "Logo_1008x1440.png", "id": "1263381491292105", "image_type": "APP_IMG_COVER_PORTRAIT", "uri": "https://scontent-sjc3-1.oculuscdn.com/v/t64.5771-25/39035391_1263381494625438_797498569855565140_n.png?_nc_cat=110&ccb=1-7&_nc_sid=6e7a0a&_nc_ohc=E-YHFHrR_LoQ7kNvwERof9U&_nc_oc=Adk9u2D5DlzU7kvUsvrbiVsUbCsPKcek6a1q-YYRFQouvb1Xk2bQKjetNRSbgSf5YR0&_nc_zt=3&_nc_ht=scontent-sjc3-1.oculuscdn.com&oh=00_AfongWok9-Sh6bO-G0brr555L-zURdEfaYQIWv9IxJrhRA&oe=695BB951"}, {"file_name": "Logo_16x9.png", "id": "1200608677716200", "image_type": "APP_IMG_COVER_LANDSCAPE", "uri": "https://scontent-sjc3-1.oculuscdn.com/v/t64.5771-25/75375081_1200608681049533_3636366679980505671_n.png?_nc_cat=102&ccb=1-7&_nc_sid=6e7a0a&_nc_ohc=rOeDGTxqENYQ7kNvwGgTjVi&_nc_oc=AdnXR8fKfwPrrDg8Dp3O2JmeCdaJii42noxt3WlLpG0LystFUTgzF59SzQOINiPvtxU&_nc_zt=3&_nc_ht=scontent-sjc3-1.oculuscdn.com&oh=00_AfqKahbW-ivOMX34-OqsfadCFo4lSUeOHuSSerfyAeYBRg&oe=695BAB63"}, {"file_name": "Logo.png", "id": "1151631356383364", "image_type": "APP_IMG_LOGO_TRANSPARENT", "uri": "https://scontent-sjc6-1.oculuscdn.com/v/t64.5771-25/75250457_1151631359716697_1929581514997661644_n.png?_nc_cat=107&ccb=1-7&_nc_sid=6e7a0a&_nc_ohc=5gSqZzL56PIQ7kNvwGtCj-s&_nc_oc=Adk6mI_jzJvTAzY0q34aR5F996xEcFDkiZVEXhqX9ms4zS2ww30yoVa1uZPnL6q5rkA&_nc_zt=3&_nc_ht=scontent-sjc6-1.oculuscdn.com&oh=00_Afrurb74FDj-bhdxJFFLn3rVvbNKWFwSmGnqB4WWOh-ctg&oe=695BA6FD"}, {"file_name": "HeroCover.png", "id": "545639141451125", "image_type": "APP_IMG_HERO", "uri": "https://scontent-sjc6-1.oculuscdn.com/v/t64.5771-25/39031314_545639144784458_2382433719123128353_n.png?_nc_cat=101&ccb=1-7&_nc_sid=6e7a0a&_nc_ohc=jtDdWDoGOvgQ7kNvwGdddAw&_nc_oc=AdlqM7YexqYySoElqOJFWvgzEcJTPEyilAD4va8XXae_1UGq1WqXi6kUeFYaJiE9KmU&_nc_zt=3&_nc_ht=scontent-sjc6-1.oculuscdn.com&oh=00_AfpiqBtCEnrarVBSlj3VDvg-d6ZSw_-D7Uk1IOl4wlTnow&oe=695B9BC5"}, {"file_name": "Logo_512x512.png", "id": "405262315657101", "image_type": "APP_IMG_ICON", "uri": "https://scontent-sjc6-1.oculuscdn.com/v/t64.5771-25/38974854_405262318990434_8156810984127282611_n.png?_nc_cat=111&ccb=1-7&_nc_sid=6e7a0a&_nc_ohc=mP_TxoGC5zgQ7kNvwH0USjk&_nc_oc=Adl-RGLPNDcqi1Yw4FvgkIpptrZrmd7CJzIwERrHuE49gyCWcDlr4QSgQzxw-0GRfQE&_nc_zt=3&_nc_ht=scontent-sjc6-1.oculuscdn.com&oh=00_AfqjgcRPU44_33_AM5m33MU6dZPr0HDyo-uZO86mOjIzog&oe=695BB8BA"}]}, "id": "521833990630289", "locale": "en_US", "screenshots": [{"file_name": "Prev1.png", "id": "426904343309550", "uri": "https://scontent-sjc3-1.oculuscdn.com/v/t64.5771-25/39036669_426904346642883_7919296481189995880_n.png?_nc_cat=100&ccb=1-7&_nc_sid=6e7a0a&_nc_ohc=rdXXMMfhz-MQ7kNvwEeV8ts&_nc_oc=AdmRXBjI6IQgRANb5YHII_pEESlK9exnFkBb9P5fF-FRunR0EYJJYN8cNc1TIFvTmWQ&_nc_zt=3&_nc_ht=scontent-sjc3-1.oculuscdn.com&oh=00_AfpIJ2fAh_CDpsybM1hWTxnKY6yp4QJMtd1PSCsGNQQyeg&oe=695BAC25"}, {"file_name": "Prev2.png", "id": "1222580455450143", "uri": "https://scontent-sjc3-1.oculuscdn.com/v/t64.5771-25/38974751_1222580458783476_6770115976318698396_n.png?_nc_cat=100&ccb=1-7&_nc_sid=6e7a0a&_nc_ohc=G6gfHrC9KOYQ7kNvwHWCT4m&_nc_oc=AdnxoXjptP9_ciMVT-03qCGNSNd_Lwt_BOqSLU2nqSc82yTZ7VFrZSKjsXEYdTa-fiA&_nc_zt=3&_nc_ht=scontent-sjc3-1.oculuscdn.com&oh=00_Afoj5dH3RPTPjCbq5Zcxe9hoLWWWsiR_eCdOWdnAoKIvlg&oe=695BA1A4"}, {"file_name": "Prev3.png", "id": "878645664451022", "uri": "https://scontent-sjc6-1.oculuscdn.com/v/t64.5771-25/39031325_878645667784355_2494646882430881744_n.png?_nc_cat=101&ccb=1-7&_nc_sid=6e7a0a&_nc_ohc=kCP1lCPJs84Q7kNvwFb2FFG&_nc_oc=AdloeFK_ltqJRCCg-_M5_yg4TpYe0LBvonxc1Ll__HeHpDbR_zNjW38LLLjmXJGW3Q0&_nc_zt=3&_nc_ht=scontent-sjc6-1.oculuscdn.com&oh=00_AfqS2jQnDAd212AA1UaRbz1_Kfn-JvyRgqxbFsKA7Yh4rg&oe=695BA766"}, {"file_name": "Prev4.png", "id": "507225855588758", "uri": "https://scontent-sjc6-1.oculuscdn.com/v/t64.5771-25/38982458_507225858922091_3504272917839192764_n.png?_nc_cat=111&ccb=1-7&_nc_sid=6e7a0a&_nc_ohc=7BRAmcZj4a8Q7kNvwGMCnZE&_nc_oc=Admg5wSHZ6tnqlQ2V05AmQ9RgsmpiT0H_Ir_-FJe27_oU8R1XfhxA-R9N3_y4i_qodU&_nc_zt=3&_nc_ht=scontent-sjc6-1.oculuscdn.com&oh=00_AfrVgINim4ZWGnPacVHw6Etp8cFa8Lc8cRqpbOFyrMDYaQ&oe=695B9CF6"}, {"file_name": "Prev5.png", "id": "522310994081129", "uri": "https://scontent-sjc3-1.oculuscdn.com/v/t64.5771-25/38974862_522310997414462_2903102651258581585_n.png?_nc_cat=106&ccb=1-7&_nc_sid=6e7a0a&_nc_ohc=xaAVlGr9kcIQ7kNvwHXPvmo&_nc_oc=AdnVQt7PRBvPP2-U_xMyWHArAD-VXWl3Ls-6fWlsB8KB3_-KVeT4xTM9KB3NlnA-rxk&_nc_zt=3&_nc_ht=scontent-sjc3-1.oculuscdn.com&oh=00_AfoYnzFg9rt3-Lhgj_oaqDg9vGR6ZtoDn64lwrPpgIC9Vg&oe=695B9D09"}], "video_trailer": null, "video_trailer_thumbnail": {"file_name": "Logo_2560x1440.png", "id": "1080821206723839", "uri": "https://scontent-sjc6-1.oculuscdn.com/v/t64.5771-25/39001694_1080821210057172_1991020744721426273_n.png?_nc_cat=104&ccb=1-7&_nc_sid=6e7a0a&_nc_ohc=SBiRh85znmYQ7kNvwHGLh5y&_nc_oc=AdlAm5WV-wWAyGDJ57fvXkhss2WXyNyVjiwnxX0o1XVyR-rKRREpg-Umj-fA9F1vNDk&_nc_zt=3&_nc_ht=scontent-sjc6-1.oculuscdn.com&oh=00_AfquA7dEZjMRj7oT72hpz7pyyd0Lsz7IJ-Q436VgtH4dEw&oe=695BA503"}, "display_name": "HandTastic", "keywords": ["Fantastic", "party", "Obstacle", "racing", "fall"], "long_description": "Welcome to Handtastic!\n\nGet ready to embark on a thrilling hand-powered adventure like no other! Grab, climb, and leap your way through a colorful world filled with exciting challenges and hilarious antics.\n\nIn Handtastic, you take control of adorable creatures with capsule-formed bodies, lively arms, and insatiable curiosity. Step into their wacky world, where the competition is fierce and the fun is endless.\n\nEngage in heart-pumping multiplayer matches across a variety of whimsical maps. Race to the finish line and outlast your opponents in your quest for hand-powered glory.\n\nJoin forces with friends in our spaceship-themed lobby, where you can team up, strategize, and dive into the action together. Embrace the silliness, enjoy the colorful visuals, and groove to the upbeat soundtracks that will keep your spirits high.\n\nSo, are you ready to unleash the power of your hands?\n\nIt's time to go hand-in-hand with excitement and embark on an unforgettable adventure in Handtastic!", "short_description": "Get ready to embark on a thrilling hand-powered adventure like no other! Grab, climb, and leap your way through a colorful world filled with exciting challenges and hilarious antics.\n\nEngage in heart-pumping multiplayer matches across a variety of whimsical maps in your quest for hand-powered glory.\n\nSo, are you ready to unleash the power of your hands? It's time to go hand-in-hand with excitement and embark on an unforgettable adventure in Handtastic!"}]}, "developer_name": null, "developer_privacy_policy_url": "https://handtasticvr.com/privacy-policy", "developer_terms_of_service_url": "https://handtasticvr.com/terms-of-service", "publisher_name": "Costo Games", "support_website_url": "https://handtasticvr.com/support", "website_url": "https://handtasticvr.com/", "category": null, "comfort_rating": "COMFORTABLE_FOR_SOME", "comfort_tags": [], "context_category": {"id": "2743326035925534", "context_category": "GAMES"}, "context_topics": [{"id": "459781504968480"}], "external_subscription_type": "NOT_REQUIRED", "genres": [], "has_in_app_ads": null, "internet_connection": "REQUIRED", "play_area": "NO_MOVEMENT", "recommended_graphics": null, "recommended_memory_gb": null, "recommended_processor": null, "supported_in_app_languages": ["en"], "supported_input_devices": ["OCULUS_TOUCH"], "supported_player_modes": ["STANDING", "ROOM_SCALE"], "supported_tracking_modes": [], "user_interaction_modes": ["SINGLE_USER", "MULTI_USER", "CO_OP"], "id": "8315319898560070"}}]}, "scheduled_offers": {"count": 5, "nodes": [{"status": "PUBLISHED", "id": "838486601432190"}, {"status": "PUBLISHED", "id": "4157891064477012"}, {"status": "PUBLISHED", "id": "1042908934576836"}, {"status": "PUBLISHED", "id": "1346311183005700"}, {"status": "PUBLISHED", "id": "1049388006887365"}]}, "baseline_offer": {"id": "4157891064477012"}, "is_approved": true, "firstOffer": {"nodes": [{"start_time": 1761591300, "status": "PUBLISHED", "id": "4157891064477012"}]}, "liveChannel": {"nodes": [{"latest_supported_binary": {"__typename": "AndroidBinary", "binary_test_results": {"nodes": []}, "id": "24864145893250876", "version": "1.0.0"}, "id": "823519099854924", "channel_name": "LIVE"}]}, "is_for_oculus_keys_only": false, "primary_binaries": {"nodes": [{"__typename": "AndroidBinary", "__isAppBinary": "AndroidBinary", "binary_application": {"__typename": "Application", "id": "8285675901524470", "is_concept": false, "latest_released_binary": {"__typename": "AndroidBinary", "id": "24864145893250876"}, "release_status": "RELEASED"}, "binary_release_channels": {"nodes": [{"channel_name": "LIVE", "id": "823519099854924"}]}, "change_log": "F2P release!\nNew Map Squeak 'n' Yeet\nOptimized models and graphics\nUpdated netcode for parties\nOverall optimized code\nNew Lobby\nNew minigame", "created_date": 1761267043, "id": "24864145893250876", "version": "1.0.0", "version_code": 1000, "release_status": "RELEASED", "status": "APPROVED", "binary_test_results": {"nodes": []}, "obb_binary": null, "asset_files": {"count": 0}, "debug_symbols": {"count": 0}, "__isAppBinaryWithFileAsset": "AndroidBinary"}, {"__typename": "AndroidBinary", "__isAppBinary": "AndroidBinary", "binary_application": {"__typename": "Application", "id": "8285675901524470", "is_concept": false, "latest_released_binary": {"__typename": "AndroidBinary", "id": "24864145893250876"}, "release_status": "RELEASED"}, "binary_release_channels": {"nodes": []}, "change_log": null, "created_date": 1761244546, "id": "24861575376841261", "version": "0.269", "version_code": 269, "release_status": "PENDING", "status": "DRAFT", "binary_test_results": {"nodes": []}, "obb_binary": null, "asset_files": {"count": 0}, "debug_symbols": {"count": 0}, "__isAppBinaryWithFileAsset": "AndroidBinary"}, {"__typename": "AndroidBinary", "__isAppBinary": "AndroidBinary", "binary_application": {"__typename": "Application", "id": "8285675901524470", "is_concept": false, "latest_released_binary": {"__typename": "AndroidBinary", "id": "24864145893250876"}, "release_status": "RELEASED"}, "binary_release_channels": {"nodes": []}, "change_log": null, "created_date": 1760898860, "id": "24822878877377578", "version": "0.268", "version_code": 268, "release_status": "PENDING", "status": "DRAFT", "binary_test_results": {"nodes": []}, "obb_binary": null, "asset_files": {"count": 0}, "debug_symbols": {"count": 0}, "__isAppBinaryWithFileAsset": "AndroidBinary"}, {"__typename": "AndroidBinary", "__isAppBinary": "AndroidBinary", "binary_application": {"__typename": "Application", "id": "8285675901524470", "is_concept": false, "latest_released_binary": {"__typename": "AndroidBinary", "id": "24864145893250876"}, "release_status": "RELEASED"}, "binary_release_channels": {"nodes": []}, "change_log": null, "created_date": 1760893974, "id": "24822295120769287", "version": "0.267", "version_code": 267, "release_status": "PENDING", "status": "DRAFT", "binary_test_results": {"nodes": []}, "obb_binary": null, "asset_files": {"count": 0}, "debug_symbols": {"count": 0}, "__isAppBinaryWithFileAsset": "AndroidBinary"}, {"__typename": "AndroidBinary", "__isAppBinary": "AndroidBinary", "binary_application": {"__typename": "Application", "id": "8285675901524470", "is_concept": false, "latest_released_binary": {"__typename": "AndroidBinary", "id": "24864145893250876"}, "release_status": "RELEASED"}, "binary_release_channels": {"nodes": []}, "change_log": null, "created_date": 1760834127, "id": "24815981418067324", "version": "0.266", "version_code": 266, "release_status": "PENDING", "status": "DRAFT", "binary_test_results": {"nodes": []}, "obb_binary": null, "asset_files": {"count": 0}, "debug_symbols": {"count": 0}, "__isAppBinaryWithFileAsset": "AndroidBinary"}]}}, "viewer": {"user": null}}}